{
    "Author": "DOCTOR_STRANGE",
    "name": "FanCode Live Matches API",
    "last_updated": "01:45:08 AM 19-07-2025",
    "headers": {
        "User-Agent": "ReactNativeVideo/7.19.1 (Linux;Android/13) AndroidXMedia3/1.1.1",
        "Referer": "https://fancode.com/"
    },
    "total_matches": 11,
    "live_matches": 8,
    "upcoming_matches": 3,
    "matches": [
        {
            "category": "Football",
            "title": "Spain Women Vs Switzerland Women",
            "tournament": "UEFA Women's EURO 2025",
            "short_name": "Women's Euro",
            "match_id": 123370,
            "status": "STARTED",
            "startTime": "19 July 2025 12:30 AM",
            "startDate": "02 July 2025 05:30 AM",
            "endDate": "27 July 2025 11:30 PM",
            "image": "https://www.fancode.com/skillup-uploads/cms-media/123370_5107_SPA-W_SWE-W_fc-app.jpg",
            "image_cdn": {
                "TATAPLAY": "https://images.fancode.com/aig/match/v1/123370_CASACARDS_PARTNER_16_9_1920_1080.png",
                "APP": "https://www.fancode.com/skillup-uploads/cms-media/123370_5107_SPA-W_SWE-W_fc-app.jpg",
                "PLAYBACK": "https://www.fancode.com/skillup-uploads/cms-media/123370_5107_SPA-W_SWE-W_fc-web.jpg",
                "CLOUDFARE": "https://d229kpbsb5jevy.cloudfront.net/vffancode2/aig/match/v1/123370_CASACARDS_PARTNER_16_9_1920_1080.png"
            },
            "teams": [
                {
                    "id": 1259,
                    "name": "Spain Women",
                    "shortName": "SPA-W",
                    "logo": "https://d13ir53smqqeyp.cloudfront.net/flags/ft-flags/FC-ESP@2x.png",
                    "flag": "https://d13ir53smqqeyp.cloudfront.net/flags/ft-flags/FC-ESP@2x.png",
                    "color": "#ffb400"
                },
                {
                    "id": 4994,
                    "name": "Switzerland Women",
                    "shortName": "SWI-W",
                    "logo": "https://d13ir53smqqeyp.cloudfront.net/flags/ft-flags/FC-SWIT@2x.png",
                    "flag": "https://d13ir53smqqeyp.cloudfront.net/flags/ft-flags/FC-SWIT@2x.png",
                    "color": "#cd2a1c"
                }
            ],
            "language": "ENGLISH",
            "adfree_stream": "https://in-mc-pdlive.fancode.com/mumbai/123370_english_hls_54392adfreeta-di_h264/index.m3u8",
            "dai_stream": "https://dai.google.com/linear/hls/event/EuitxsWEQ8iyk7JGEfZ_4w/master.m3u8",
            "STREAMING_CDN": {
                "Primary_Playback_URL": "https://in-mc-pdlive.fancode.com/mumbai/123370_english_hls_54392adfreeta-di_h264/index.m3u8",
                "fancode_cdn": "https://in-mc-pdlive.fancode.com/mumbai/123370_english_hls_54392adfreeta-di_h264/index.m3u8",
                "dai_google_cdn": "https://dai.google.com/linear/hls/event/EuitxsWEQ8iyk7JGEfZ_4w/master.m3u8",
                "cloudfront_cdn": "Unavailable",
                "language": "ENGLISH"
            }
        },
        {
            "category": "Cricket",
            "title": "Somerset Vs Gloucestershire",
            "tournament": "Vitality Blast T20, 2025",
            "short_name": "Vitality Blast T20",
            "match_id": 126010,
            "status": "STARTED",
            "startTime": "18 July 2025 11:00 PM",
            "startDate": "29 May 2025 05:30 AM",
            "endDate": "13 September 2025 05:30 AM",
            "image": "https://www.fancode.com/skillup-uploads/cms-media/126010_5207_SOM_GLO_fc-App.jpg",
            "image_cdn": {
                "TATAPLAY": "https://images.fancode.com/aig/match/v1/126010_CASACARDS_PARTNER_16_9_1920_1080.png",
                "APP": "https://www.fancode.com/skillup-uploads/cms-media/126010_5207_SOM_GLO_fc-App.jpg",
                "PLAYBACK": null,
                "CLOUDFARE": "https://d229kpbsb5jevy.cloudfront.net/vffancode2/aig/match/v1/126010_CASACARDS_PARTNER_16_9_1920_1080.png"
            },
            "teams": [
                {
                    "id": 282,
                    "name": "Somerset",
                    "shortName": "SOM",
                    "logo": "https://d13ir53smqqeyp.cloudfront.net/flags/cr-flags/FC-SOM@2x.png",
                    "flag": "https://d13ir53smqqeyp.cloudfront.net/flags/cr-flags/FC-SOM@2x.png",
                    "color": "#a93653"
                },
                {
                    "id": 363,
                    "name": "Gloucestershire",
                    "shortName": "GLO",
                    "logo": "https://d13ir53smqqeyp.cloudfront.net/flags/cr-flags/FC-GLO@2x.png",
                    "flag": "https://d13ir53smqqeyp.cloudfront.net/flags/cr-flags/FC-GLO@2x.png",
                    "color": "#17836e"
                }
            ],
            "language": "ENGLISH",
            "adfree_stream": "https://in-mc-pdlive.fancode.com/mumbai/126010_english_hls_72733adfreeta-di_h264/index.m3u8",
            "dai_stream": "https://dai.google.com/linear/hls/event/SrTvRdkKRiupW2jrkMQm1g/master.m3u8",
            "STREAMING_CDN": {
                "Primary_Playback_URL": "https://in-mc-pdlive.fancode.com/mumbai/126010_english_hls_72733adfreeta-di_h264/index.m3u8",
                "fancode_cdn": "https://in-mc-pdlive.fancode.com/mumbai/126010_english_hls_72733adfreeta-di_h264/index.m3u8",
                "dai_google_cdn": "https://dai.google.com/linear/hls/event/SrTvRdkKRiupW2jrkMQm1g/master.m3u8",
                "cloudfront_cdn": "Unavailable",
                "language": "ENGLISH"
            }
        },
        {
            "category": "Cricket",
            "title": "Nottinghamshire Vs Lancashire",
            "tournament": "Vitality Blast T20, 2025",
            "short_name": "Vitality Blast T20",
            "match_id": 126009,
            "status": "STARTED",
            "startTime": "18 July 2025 11:00 PM",
            "startDate": "29 May 2025 05:30 AM",
            "endDate": "13 September 2025 05:30 AM",
            "image": "https://www.fancode.com/skillup-uploads/cms-media/Nottinghamshire-vs-Lancashire-sporty.png",
            "image_cdn": {
                "TATAPLAY": "https://images.fancode.com/aig/match/v1/126009_CASACARDS_PARTNER_16_9_1920_1080.png",
                "APP": "https://www.fancode.com/skillup-uploads/cms-media/Nottinghamshire-vs-Lancashire-sporty.png",
                "PLAYBACK": "https://www.fancode.com/skillup-uploads/cms-media/Nottinghamshire-vs-Lancashire-old.png",
                "CLOUDFARE": "https://d229kpbsb5jevy.cloudfront.net/vffancode2/aig/match/v1/126009_CASACARDS_PARTNER_16_9_1920_1080.png"
            },
            "teams": [
                {
                    "id": 368,
                    "name": "Nottinghamshire",
                    "shortName": "NOT",
                    "logo": "https://d13ir53smqqeyp.cloudfront.net/flags/cr-flags/FC-NOT@2x.png",
                    "flag": "https://d13ir53smqqeyp.cloudfront.net/flags/cr-flags/FC-NOT@2x.png",
                    "color": "#449438"
                },
                {
                    "id": 364,
                    "name": "Lancashire",
                    "shortName": "LAN",
                    "logo": "https://d13ir53smqqeyp.cloudfront.net/flags/cr-flags/FC-LAN@2x.png",
                    "flag": "https://d13ir53smqqeyp.cloudfront.net/flags/cr-flags/FC-LAN@2x.png",
                    "color": "#e9515e"
                }
            ],
            "language": "ENGLISH",
            "adfree_stream": "https://dai.google.com/linear/hls/event/2wNKn5gLSaqxNWiqsz7-vQ/master.m3u8",
            "dai_stream": "https://dai.google.com/linear/hls/event/2wNKn5gLSaqxNWiqsz7-vQ/master.m3u8",
            "STREAMING_CDN": {
                "Primary_Playback_URL": "https://dai.google.com/linear/hls/event/2wNKn5gLSaqxNWiqsz7-vQ/master.m3u8",
                "fancode_cdn": "Unavailable",
                "dai_google_cdn": "https://dai.google.com/linear/hls/event/2wNKn5gLSaqxNWiqsz7-vQ/master.m3u8",
                "cloudfront_cdn": "Unavailable",
                "language": "ENGLISH"
            }
        },
        {
            "category": "Cricket",
            "title": "Glamorgan Vs Middlesex",
            "tournament": "Vitality Blast T20, 2025",
            "short_name": "Vitality Blast T20",
            "match_id": 126006,
            "status": "STARTED",
            "startTime": "18 July 2025 11:00 PM",
            "startDate": "29 May 2025 05:30 AM",
            "endDate": "13 September 2025 05:30 AM",
            "image": "https://www.fancode.com/skillup-uploads/cms-media/126006_5207_GLA_MID_fc-App.jpg",
            "image_cdn": {
                "TATAPLAY": "https://images.fancode.com/aig/match/v1/126006_CASACARDS_PARTNER_16_9_1920_1080.png",
                "APP": "https://www.fancode.com/skillup-uploads/cms-media/126006_5207_GLA_MID_fc-App.jpg",
                "PLAYBACK": "https://www.fancode.com/skillup-uploads/cms-media/126006_5207_GLA_MID_fc-Web.jpg",
                "CLOUDFARE": "https://d229kpbsb5jevy.cloudfront.net/vffancode2/aig/match/v1/126006_CASACARDS_PARTNER_16_9_1920_1080.png"
            },
            "teams": [
                {
                    "id": 362,
                    "name": "Glamorgan",
                    "shortName": "GLA",
                    "logo": "https://d13ir53smqqeyp.cloudfront.net/flags/cr-flags/FC-GLA@2x.png",
                    "flag": "https://d13ir53smqqeyp.cloudfront.net/flags/cr-flags/FC-GLA@2x.png",
                    "color": "#528c3d"
                },
                {
                    "id": 366,
                    "name": "Middlesex",
                    "shortName": "MID",
                    "logo": "https://d13ir53smqqeyp.cloudfront.net/flags/cr-flags/FC-MID@2x.png",
                    "flag": "https://d13ir53smqqeyp.cloudfront.net/flags/cr-flags/FC-MID@2x.png",
                    "color": "#2d4475"
                }
            ],
            "language": "ENGLISH",
            "adfree_stream": "https://in-mc-pdlive.fancode.com/mumbai/126006_english_hls_29823adfreeta-di_h264/index.m3u8",
            "dai_stream": "https://dai.google.com/linear/hls/event/-ZnLkTZfQcqG0hXFR5R0Ow/master.m3u8",
            "STREAMING_CDN": {
                "Primary_Playback_URL": "https://in-mc-pdlive.fancode.com/mumbai/126006_english_hls_29823adfreeta-di_h264/index.m3u8",
                "fancode_cdn": "https://in-mc-pdlive.fancode.com/mumbai/126006_english_hls_29823adfreeta-di_h264/index.m3u8",
                "dai_google_cdn": "https://dai.google.com/linear/hls/event/-ZnLkTZfQcqG0hXFR5R0Ow/master.m3u8",
                "cloudfront_cdn": "Unavailable",
                "language": "ENGLISH"
            }
        },
        {
            "category": "Cricket",
            "title": "Durham Vs Northamptonshire",
            "tournament": "Vitality Blast T20, 2025",
            "short_name": "Vitality Blast T20",
            "match_id": 126005,
            "status": "STARTED",
            "startTime": "18 July 2025 11:00 PM",
            "startDate": "29 May 2025 05:30 AM",
            "endDate": "13 September 2025 05:30 AM",
            "image": "https://www.fancode.com/skillup-uploads/cms-media/126005_5207_DUR_NOR_fc-App.jpg",
            "image_cdn": {
                "TATAPLAY": "https://images.fancode.com/aig/match/v1/126005_CASACARDS_PARTNER_16_9_1920_1080.png",
                "APP": "https://www.fancode.com/skillup-uploads/cms-media/126005_5207_DUR_NOR_fc-App.jpg",
                "PLAYBACK": "https://www.fancode.com/skillup-uploads/cms-media/126005_5207_DUR_NOR_fc-Web.jpg",
                "CLOUDFARE": "https://d229kpbsb5jevy.cloudfront.net/vffancode2/aig/match/v1/126005_CASACARDS_PARTNER_16_9_1920_1080.png"
            },
            "teams": [
                {
                    "id": 360,
                    "name": "Durham",
                    "shortName": "DUR",
                    "logo": "https://d13ir53smqqeyp.cloudfront.net/flags/cr-flags/FC-DURC@2x.png",
                    "flag": "https://d13ir53smqqeyp.cloudfront.net/flags/cr-flags/FC-DURC@2x.png",
                    "color": "#8c8301"
                },
                {
                    "id": 295,
                    "name": "Northamptonshire",
                    "shortName": "NOR",
                    "logo": "https://d13ir53smqqeyp.cloudfront.net/flags/cr-flags/FC-NORT@2x.png",
                    "flag": "https://d13ir53smqqeyp.cloudfront.net/flags/cr-flags/FC-NORT@2x.png",
                    "color": "#912854"
                }
            ],
            "language": "ENGLISH",
            "adfree_stream": "https://in-mc-pdlive.fancode.com/mumbai/126005_english_hls_16232adfreeta-di_h264/index.m3u8",
            "dai_stream": "https://dai.google.com/linear/hls/event/eXfUXnGgSqmDIgMreTEbrw/master.m3u8",
            "STREAMING_CDN": {
                "Primary_Playback_URL": "https://in-mc-pdlive.fancode.com/mumbai/126005_english_hls_16232adfreeta-di_h264/index.m3u8",
                "fancode_cdn": "https://in-mc-pdlive.fancode.com/mumbai/126005_english_hls_16232adfreeta-di_h264/index.m3u8",
                "dai_google_cdn": "https://dai.google.com/linear/hls/event/eXfUXnGgSqmDIgMreTEbrw/master.m3u8",
                "cloudfront_cdn": "Unavailable",
                "language": "ENGLISH"
            }
        },
        {
            "category": "Cricket",
            "title": "Vegas Vikings Vs Cayman Bay Stingrays",
            "tournament": "Max60 Season 2, 2025",
            "short_name": "Max60",
            "match_id": 131722,
            "status": "STARTED",
            "startTime": "19 July 2025 01:00 AM",
            "startDate": "16 July 2025 05:30 AM",
            "endDate": "23 July 2025 05:30 AM",
            "image": "https://www.fancode.com/skillup-uploads/cms-media/131458_5453_VEV_CBS_fc-App.jpg",
            "image_cdn": {
                "TATAPLAY": "https://images.fancode.com/aig/match/v1/131722_CASACARDS_PARTNER_16_9_1920_1080.png",
                "APP": "https://www.fancode.com/skillup-uploads/cms-media/131458_5453_VEV_CBS_fc-App.jpg",
                "PLAYBACK": "https://www.fancode.com/skillup-uploads/cms-media/131458_5453_VEV_CBS_fc-Web.jpg",
                "CLOUDFARE": "https://d229kpbsb5jevy.cloudfront.net/vffancode2/aig/match/v1/131722_CASACARDS_PARTNER_16_9_1920_1080.png"
            },
            "teams": [
                {
                    "id": 11725,
                    "name": "Vegas Vikings",
                    "shortName": "VEV",
                    "logo": "https://d13ir53smqqeyp.cloudfront.net/flags/cr-flags/FC-VEV@2x.png",
                    "flag": "https://d13ir53smqqeyp.cloudfront.net/flags/cr-flags/FC-VEV@2x.png",
                    "color": "#2b73d3"
                },
                {
                    "id": 11720,
                    "name": "Cayman Bay Stingrays",
                    "shortName": "CBS",
                    "logo": "https://d13ir53smqqeyp.cloudfront.net/flags/cr-flags/FC-CBS@2x.png",
                    "flag": "https://d13ir53smqqeyp.cloudfront.net/flags/cr-flags/FC-CBS@2x.png",
                    "color": "#009cff"
                }
            ],
            "language": "ENGLISH",
            "adfree_stream": "https://in-mc-pdlive.fancode.com/mumbai/131722_english_hls_7461adfreeta-di_h264/index.m3u8",
            "dai_stream": "https://dai.google.com/linear/hls/event/arUkVnVvQq6wQxT_25jh-Q/master.m3u8",
            "STREAMING_CDN": {
                "Primary_Playback_URL": "https://in-mc-pdlive.fancode.com/mumbai/131722_english_hls_7461adfreeta-di_h264/index.m3u8",
                "fancode_cdn": "https://in-mc-pdlive.fancode.com/mumbai/131722_english_hls_7461adfreeta-di_h264/index.m3u8",
                "dai_google_cdn": "https://dai.google.com/linear/hls/event/arUkVnVvQq6wQxT_25jh-Q/master.m3u8",
                "cloudfront_cdn": "Unavailable",
                "language": "ENGLISH"
            }
        },
        {
            "category": "Cricket",
            "title": "Caribbean Tigers Vs Florida Lions",
            "tournament": "Max60 Season 2, 2025",
            "short_name": "Max60",
            "match_id": 131725,
            "status": "NOT_STARTED",
            "startTime": "19 July 2025 03:00 AM",
            "startDate": "16 July 2025 05:30 AM",
            "endDate": "23 July 2025 05:30 AM",
            "image": "https://www.fancode.com/skillup-uploads/cms-media/131461_5453_CAT_FLI_fc-App.jpg",
            "image_cdn": {
                "TATAPLAY": "https://images.fancode.com/aig/match/v1/131725_CASACARDS_PARTNER_16_9_1920_1080.png",
                "APP": "https://www.fancode.com/skillup-uploads/cms-media/131461_5453_CAT_FLI_fc-App.jpg",
                "PLAYBACK": null,
                "CLOUDFARE": "https://d229kpbsb5jevy.cloudfront.net/vffancode2/aig/match/v1/131725_CASACARDS_PARTNER_16_9_1920_1080.png"
            },
            "teams": [
                {
                    "id": 8931,
                    "name": "Caribbean Tigers",
                    "shortName": "CAT",
                    "logo": "https://d13ir53smqqeyp.cloudfront.net/flags/cr-flags/FC-CAT@2x.png",
                    "flag": "https://d13ir53smqqeyp.cloudfront.net/flags/cr-flags/FC-CAT@2x.png",
                    "color": "#b9160c"
                },
                {
                    "id": 11724,
                    "name": "Florida Lions",
                    "shortName": "FLI",
                    "logo": "https://d13ir53smqqeyp.cloudfront.net/flags/cr-flags/FC-FLI@2x.png",
                    "flag": "https://d13ir53smqqeyp.cloudfront.net/flags/cr-flags/FC-FLI@2x.png",
                    "color": "#63b5e4"
                }
            ],
            "language": "BLOODY_SWEET",
            "adfree_stream": null,
            "dai_stream": null,
            "STREAMING_CDN": {
                "language": "BLOODY_SWEET",
                "Primary_Playback_URL": null
            }
        },
        {
            "category": "Cricket",
            "title": "Guyana Amazon Warriors Vs Rangpur Riders",
            "tournament": "Global Super League, 2025",
            "short_name": "GSL",
            "match_id": 130490,
            "status": "NOT_STARTED",
            "startTime": "19 July 2025 04:30 AM",
            "startDate": "10 July 2025 05:30 AM",
            "endDate": "18 July 2025 05:30 AM",
            "image": "https://www.fancode.com/skillup-uploads/cms-media/130481_5402_GUY_RAN_fc-App.jpg",
            "image_cdn": {
                "TATAPLAY": "https://images.fancode.com/aig/match/v1/130490_CASACARDS_PARTNER_16_9_1920_1080.png",
                "APP": "https://www.fancode.com/skillup-uploads/cms-media/130481_5402_GUY_RAN_fc-App.jpg",
                "PLAYBACK": null,
                "CLOUDFARE": "https://d229kpbsb5jevy.cloudfront.net/vffancode2/aig/match/v1/130490_CASACARDS_PARTNER_16_9_1920_1080.png"
            },
            "teams": [
                {
                    "id": 290,
                    "name": "Guyana Amazon Warriors",
                    "shortName": "GUY",
                    "logo": "https://d13ir53smqqeyp.cloudfront.net/flags/cr-flags/FC-GUWA@2x.png",
                    "flag": "https://d13ir53smqqeyp.cloudfront.net/flags/cr-flags/FC-GUWA@2x.png",
                    "color": "#b01018"
                },
                {
                    "id": 326,
                    "name": "Rangpur Riders",
                    "shortName": "RAN",
                    "logo": "https://d13ir53smqqeyp.cloudfront.net/flags/cr-flags/FC-RANG@2x.png",
                    "flag": "https://d13ir53smqqeyp.cloudfront.net/flags/cr-flags/FC-RANG@2x.png",
                    "color": "#42b7e8"
                }
            ],
            "language": "BLOODY_SWEET",
            "adfree_stream": null,
            "dai_stream": null,
            "STREAMING_CDN": {
                "language": "BLOODY_SWEET",
                "Primary_Playback_URL": null
            }
        },
        {
            "category": "Cricket",
            "title": "England Women Vs India Women",
            "tournament": "India Women tour of England, 2025",
            "short_name": "ENG-W vs IND-W",
            "match_id": 128746,
            "status": "NOT_STARTED",
            "startTime": "19 July 2025 03:30 PM",
            "startDate": "28 June 2025 05:30 AM",
            "endDate": "22 July 2025 05:30 AM",
            "image": "https://www.fancode.com/skillup-uploads/cms-media/ENG-Vs-IND_ODI-SERIES_2025_TV_vertical_.jpg",
            "image_cdn": {
                "TATAPLAY": "https://images.fancode.com/aig/match/v1/128746_CASACARDS_PARTNER_16_9_1920_1080.png",
                "APP": "https://www.fancode.com/skillup-uploads/cms-media/ENG-Vs-IND_ODI-SERIES_2025_TV_vertical_.jpg",
                "PLAYBACK": null,
                "CLOUDFARE": "https://d229kpbsb5jevy.cloudfront.net/vffancode2/aig/match/v1/128746_CASACARDS_PARTNER_16_9_1920_1080.png"
            },
            "teams": [
                {
                    "id": 646,
                    "name": "England Women",
                    "shortName": "EN-W",
                    "logo": "https://d13ir53smqqeyp.cloudfront.net/flags/cr-flags/FC-ENG@2x.png",
                    "flag": "https://d13ir53smqqeyp.cloudfront.net/flags/cr-flags/FC-ENG@2x.png",
                    "color": "#3c9ae8"
                },
                {
                    "id": 710,
                    "name": "India Women",
                    "shortName": "IN-W",
                    "logo": "https://d13ir53smqqeyp.cloudfront.net/flags/cr-flags/FC-IND@2x.png",
                    "flag": "https://d13ir53smqqeyp.cloudfront.net/flags/cr-flags/FC-IND@2x.png",
                    "color": "#0f60de"
                }
            ],
            "language": "BLOODY_SWEET",
            "adfree_stream": null,
            "dai_stream": null,
            "STREAMING_CDN": {
                "language": "BLOODY_SWEET",
                "Primary_Playback_URL": null
            }
        },
        {
            "category": "Cricket",
            "title": "Mec Study Group Vs Bader & Nie Cricket Club",
            "tournament": "KCC T20 Summer League, 2025",
            "short_name": "KCC T20 Summer League",
            "match_id": 130002,
            "status": "STARTED",
            "startTime": "19 July 2025 12:30 AM",
            "startDate": "05 July 2025 05:30 AM",
            "endDate": "08 August 2025 05:30 AM",
            "image": "https://www.fancode.com/skillup-uploads/cms-media/130002_5379_MEC_BNC_fc-web.jpg",
            "image_cdn": {
                "TATAPLAY": "https://images.fancode.com/aig/match/v1/130002_CASACARDS_PARTNER_16_9_1920_1080.png",
                "APP": "https://www.fancode.com/skillup-uploads/cms-media/130002_5379_MEC_BNC_fc-web.jpg",
                "PLAYBACK": "https://www.fancode.com/skillup-uploads/cms-media/130002_5379_MEC_BNC_fc-web.jpg",
                "CLOUDFARE": "https://d229kpbsb5jevy.cloudfront.net/vffancode2/aig/match/v1/130002_CASACARDS_PARTNER_16_9_1920_1080.png"
            },
            "teams": [
                {
                    "id": 6244,
                    "name": "MEC Study Group",
                    "shortName": "MEC",
                    "logo": "https://d13ir53smqqeyp.cloudfront.net/flags/cr-flags/FC-MSTG@2x.png",
                    "flag": "https://d13ir53smqqeyp.cloudfront.net/flags/cr-flags/FC-MSTG@2x.png",
                    "color": "#ffc300"
                },
                {
                    "id": 8322,
                    "name": "Bader & Nie Cricket Club",
                    "shortName": "BNC",
                    "logo": "https://d13ir53smqqeyp.cloudfront.net/flags/cr-flags/FC-BNC@2x.png",
                    "flag": "https://d13ir53smqqeyp.cloudfront.net/flags/cr-flags/FC-BNC@2x.png",
                    "color": "#0d395a"
                }
            ],
            "language": "ENGLISH",
            "adfree_stream": "https://in-mc-pdlive.fancode.com/mumbai/130002_english_hls_1093adfreeta-di_h264/index.m3u8",
            "dai_stream": "https://dai.google.com/linear/hls/event/-HO7C-l-St2w3lWxezZ2Ww/master.m3u8",
            "STREAMING_CDN": {
                "Primary_Playback_URL": "https://in-mc-pdlive.fancode.com/mumbai/130002_english_hls_1093adfreeta-di_h264/index.m3u8",
                "fancode_cdn": "https://in-mc-pdlive.fancode.com/mumbai/130002_english_hls_1093adfreeta-di_h264/index.m3u8",
                "dai_google_cdn": "https://dai.google.com/linear/hls/event/-HO7C-l-St2w3lWxezZ2Ww/master.m3u8",
                "cloudfront_cdn": "Unavailable",
                "language": "ENGLISH"
            }
        },
        {
            "category": "Baseball",
            "title": "Chicago Cubs Vs Boston Red Sox",
            "tournament": "Major League Baseball, 2025",
            "short_name": "Major League Baseball",
            "match_id": 130311,
            "status": "STARTED",
            "startTime": "18 July 2025 11:50 PM",
            "startDate": "18 March 2025 05:30 AM",
            "endDate": "31 October 2025 05:30 AM",
            "image": "https://images.fancode.com/aig/match/v1/130311_CASACARDS_APP.png",
            "image_cdn": {
                "TATAPLAY": "https://images.fancode.com/aig/match/v1/130311_CASACARDS_PARTNER_16_9_1920_1080.png",
                "APP": "https://images.fancode.com/aig/match/v1/130311_CASACARDS_APP.png",
                "PLAYBACK": "https://images.fancode.com/aig/match/v1/130311_CASACARDS_APP.png",
                "CLOUDFARE": "https://d229kpbsb5jevy.cloudfront.net/vffancode2/aig/match/v1/130311_CASACARDS_PARTNER_16_9_1920_1080.png"
            },
            "teams": [
                {
                    "id": 2339,
                    "name": "Chicago Cubs",
                    "shortName": "CHC",
                    "logo": "https://d13ir53smqqeyp.cloudfront.net/flags/bb-flags/FC-CHIC@2x.png",
                    "flag": "https://d13ir53smqqeyp.cloudfront.net/flags/bb-flags/FC-CHIC@2x.png",
                    "color": "#d64140"
                },
                {
                    "id": 2323,
                    "name": "Boston Red Sox",
                    "shortName": "BRS",
                    "logo": "https://d13ir53smqqeyp.cloudfront.net/flags/bb-flags/FC-BOSTON@2x.png",
                    "flag": "https://d13ir53smqqeyp.cloudfront.net/flags/bb-flags/FC-BOSTON@2x.png",
                    "color": "#97182d"
                }
            ],
            "language": "ENGLISH",
            "adfree_stream": "https://in-mc-plive.fancode.com/mumbai/130311_english_hls_58035adfreeta-di_h264/index.m3u8",
            "dai_stream": "Unavailable",
            "STREAMING_CDN": {
                "Primary_Playback_URL": "https://in-mc-plive.fancode.com/mumbai/130311_english_hls_58035adfreeta-di_h264/index.m3u8",
                "fancode_cdn": "https://in-mc-plive.fancode.com/mumbai/130311_english_hls_58035adfreeta-di_h264/index.m3u8",
                "dai_google_cdn": "Unavailable",
                "cloudfront_cdn": "Unavailable",
                "language": "ENGLISH"
            }
        }
    ]
}